xlextract/__init__.py
xlextract/classes.py
xlextract-0.2.1.dist-info/METADATA
xlextract-0.2.1.dist-info/WHEEL
xlextract-0.2.1.dist-info/RECORD
