Metadata-Version: 2.3
Name: xlextract
Version: 0.2.1
Summary: Extract data from Excel files
Author: AJ Cruz
Author-email: aj.cruz@computacenter.com
Requires-Python: >=3.11
Classifier: Programming Language :: Python :: 3
Classifier: Programming Language :: Python :: 3.11
Classifier: Programming Language :: Python :: 3.12
Classifier: Programming Language :: Python :: 3.13
Requires-Dist: openpyxl (>=3.1.5,<4.0.0)
